pyzdd_.cpython-311-x86_64-linux-gnu.so
pyzdd-0.3.0.dist-info/LICENSE
pyzdd-0.3.0.dist-info/RECORD
pyzdd-0.3.0.dist-info/top_level.txt
pyzdd-0.3.0.dist-info/WHEEL
pyzdd-0.3.0.dist-info/METADATA
pyzdd/structure.py
pyzdd/graph.py
pyzdd/__init__.py
pyzdd/_version.py
