Metadata-Version: 2.1
Name: pyzdd
Version: 0.3.0
Summary: Python wrapper to TdZdd
Home-page: https://github.com/lan496/pyzdd
Author: Kohei Shinohara
Author-email: kohei19950508@gmail.com
License: MIT
Classifier: Development Status :: 2 - Pre-Alpha
Classifier: Intended Audience :: Science/Research
Classifier: License :: OSI Approved :: MIT License
Classifier: Operating System :: POSIX :: Linux
Classifier: Operating System :: MacOS
Classifier: Programming Language :: Python
Classifier: Programming Language :: Python :: 3.8
Classifier: Programming Language :: Python :: 3.9
Classifier: Programming Language :: Python :: 3.10
Classifier: Topic :: Scientific/Engineering
Requires-Python: >=3.8
License-File: LICENSE
Requires-Dist: setuptools
Requires-Dist: setuptools_scm
Requires-Dist: wheel
Requires-Dist: networkx>=2.0
Provides-Extra: dev
Requires-Dist: cibuildwheel; extra == "dev"
Requires-Dist: ipython; extra == "dev"
Requires-Dist: pre-commit; extra == "dev"
Requires-Dist: black; extra == "dev"
Requires-Dist: versioneer; extra == "dev"
Requires-Dist: pytest; extra == "dev"
Requires-Dist: pytest-cov; extra == "dev"
Requires-Dist: flake8; extra == "dev"
Requires-Dist: mypy; extra == "dev"
Requires-Dist: isort; extra == "dev"
Requires-Dist: pyupgrade; extra == "dev"
